NaaVRE_communicator_jupyterlab/__init__.py
NaaVRE_communicator_jupyterlab/_version.py
NaaVRE_communicator_jupyterlab/handlers.py
NaaVRE_communicator_jupyterlab/tests/__init__.py
NaaVRE_communicator_jupyterlab/tests/test_handlers.py
NaaVRE_communicator_jupyterlab/utils/__init__.py
NaaVRE_communicator_jupyterlab/utils/oauth_token.py
naavre_communicator_jupyterlab-0.3.3.data/data/etc/jupyter/jupyter_server_config.d/NaaVRE_communicator_jupyterlab.json
naavre_communicator_jupyterlab-0.3.3.data/data/share/jupyter/labextensions/@naavre/communicator-jupyterlab/package.json
naavre_communicator_jupyterlab-0.3.3.data/data/share/jupyter/labextensions/@naavre/communicator-jupyterlab/static/675.2d7ba1f88f56afdf5c12.js
naavre_communicator_jupyterlab-0.3.3.data/data/share/jupyter/labextensions/@naavre/communicator-jupyterlab/static/728.7f3f37012d1eb2604592.js
naavre_communicator_jupyterlab-0.3.3.data/data/share/jupyter/labextensions/@naavre/communicator-jupyterlab/static/remoteEntry.e3c59b754e925ea02374.js
naavre_communicator_jupyterlab-0.3.3.data/data/share/jupyter/labextensions/@naavre/communicator-jupyterlab/static/style.js
naavre_communicator_jupyterlab-0.3.3.data/data/share/jupyter/labextensions/@naavre/communicator-jupyterlab/static/third-party-licenses.json
naavre_communicator_jupyterlab-0.3.3.data/data/share/jupyter/labextensions/@naavre/communicator-jupyterlab/install.json
naavre_communicator_jupyterlab-0.3.3.dist-info/METADATA
naavre_communicator_jupyterlab-0.3.3.dist-info/WHEEL
naavre_communicator_jupyterlab-0.3.3.dist-info/licenses/LICENSE
naavre_communicator_jupyterlab-0.3.3.dist-info/RECORD
