Metadata-Version: 2.4
Name: NaaVRE_communicator_jupyterlab
Version: 0.3.3
Summary: Communication gateway for NaaVRE JupyterLab extensions
Project-URL: Homepage, https://github.com/NaaVRE/NaaVRE-communicator-jupyterlab
Project-URL: Bug Tracker, https://github.com/NaaVRE/NaaVRE-communicator-jupyterlab/issues
Project-URL: Repository, https://github.com/NaaVRE/NaaVRE-communicator-jupyterlab.git
Author-email: LifeWatch ERIC VLIC & QCDIS team at University of Amsterdam <gabriel.pelouze@lifewatch.eu>
License: 
License-File: LICENSE
Keywords: jupyter,jupyterlab,jupyterlab-extension
Classifier: Framework :: Jupyter
Classifier: Framework :: Jupyter :: JupyterLab
Classifier: Framework :: Jupyter :: JupyterLab :: 4
Classifier: Framework :: Jupyter :: JupyterLab :: Extensions
Classifier: Framework :: Jupyter :: JupyterLab :: Extensions :: Prebuilt
Classifier: License :: OSI Approved :: Apache Software License
Classifier: Programming Language :: Python
Classifier: Programming Language :: Python :: 3
Classifier: Programming Language :: Python :: 3.8
Classifier: Programming Language :: Python :: 3.9
Classifier: Programming Language :: Python :: 3.10
Classifier: Programming Language :: Python :: 3.11
Classifier: Programming Language :: Python :: 3.12
Requires-Python: >=3.8
Requires-Dist: httpx==0.28.1
Requires-Dist: jupyter-server<3,>=2.0.1
Requires-Dist: pyjwt[crypto]==2.10.1
Provides-Extra: test
Requires-Dist: coverage; extra == 'test'
Requires-Dist: pytest; extra == 'test'
Requires-Dist: pytest-asyncio; extra == 'test'
Requires-Dist: pytest-cov; extra == 'test'
Requires-Dist: pytest-jupyter[server]>=0.6.0; extra == 'test'
